doodle/__init__.py
doodle/calibrations/__init__.py
doodle/calibrations/gamma_camera.py
doodle/dicomtools/__init__.py
doodle/dicomtools/dicomtools.py
doodle/dosimetry/BaseDosimetry.py
doodle/dosimetry/BoneMarrow.py
doodle/dosimetry/OrganSDosimetry.py
doodle/dosimetry/VoxelSDosimetry.py
doodle/dosimetry/__init__.py
doodle/dosimetry/dosiomicsclass.py
doodle/dosimetry/dvk.py
doodle/dosimetry/image_analysis.py
doodle/dosimetry/mc.py
doodle/dosimetry/olinda.py
doodle/dosimetry/patientdosimetry.py
doodle/dosimetry/pr21_dataframes.py
doodle/fits/__init__.py
doodle/fits/fits.py
doodle/fits/functions.py
doodle/kernels/DK_corticalboneICRP_mGyperMBqs.hdr
doodle/kernels/DK_corticalboneICRP_mGyperMBqs.img
doodle/kernels/DK_corticalboneICRP_mGyperdecay.hdr
doodle/kernels/DK_corticalboneICRP_mGyperdecay.img
doodle/kernels/DK_softtissueICRP_mGyperMBqs.hdr
doodle/kernels/DK_softtissueICRP_mGyperMBqs.img
doodle/kernels/DK_softtissueICRP_mGyperdecay.hdr
doodle/kernels/DK_softtissueICRP_mGyperdecay.img
doodle/kernels/DKcorticaIboneCRPmGyperMBqs.dcm
doodle/kernels/DKsofttissueICRPmGyperMBqs.dcm
doodle/plots/__init__.py
doodle/plots/plots.py
doodle/qc/__init__.py
doodle/qc/dosecal_qc.py
doodle/qc/planar_qc.py
doodle/qc/qc.py
doodle/qc/spect_qc.py
doodle/registration/PhantomToCT.py
doodle/registration/__init__.py
doodle/registration/demons.py
doodle/segmentation/__init__.py
doodle/segmentation/tools.py
doodle/shared/__init__.py
doodle/shared/corrections.py
doodle/shared/evaluation_metrics.py
doodle/shared/radioactive_decay.py
PyTheranostics-0.1.dist-info/LICENSE
PyTheranostics-0.1.dist-info/METADATA
PyTheranostics-0.1.dist-info/WHEEL
PyTheranostics-0.1.dist-info/top_level.txt
PyTheranostics-0.1.dist-info/RECORD
